MANIFEST.in
README.rst
setup.py
bawa.egg-info/PKG-INFO
bawa.egg-info/SOURCES.txt
bawa.egg-info/dependency_links.txt
bawa.egg-info/not-zip-safe
bawa.egg-info/requires.txt
bawa.egg-info/top_level.txt
simplepro/__init__.py
simplepro/admin.py
simplepro/apps.py
simplepro/conf.py
simplepro/filters.py
simplepro/forms.py
simplepro/handlers.py
simplepro/middlewares.py
simplepro/models.py
simplepro/simplepro.so
simplepro/urls.py
simplepro/utils.py
simplepro/__pycache__/__init__.cpython-37.pyc
simplepro/group/utils.py
simplepro/group/view.py
simplepro/static/.DS_Store
simplepro/static/admin/.DS_Store
simplepro/static/admin/group/js/group.js
simplepro/static/admin/simplepro/.DS_Store
simplepro/static/admin/simplepro/css/active.css
simplepro/static/admin/simplepro/css/active.css.map
simplepro/static/admin/simplepro/css/active.less
simplepro/static/admin/simplepro/css/editor.css
simplepro/static/admin/simplepro/css/editor.css.map
simplepro/static/admin/simplepro/css/editor.less
simplepro/static/admin/simplepro/css/home.css
simplepro/static/admin/simplepro/css/home.css.map
simplepro/static/admin/simplepro/css/home.less
simplepro/static/admin/simplepro/css/index.css
simplepro/static/admin/simplepro/css/index.css.map
simplepro/static/admin/simplepro/css/index.less
simplepro/static/admin/simplepro/css/list.css
simplepro/static/admin/simplepro/css/list.css.map
simplepro/static/admin/simplepro/css/list.less
simplepro/static/admin/simplepro/css/login.css
simplepro/static/admin/simplepro/css/login.css.map
simplepro/static/admin/simplepro/css/login.less
simplepro/static/admin/simplepro/echarts/echarts-en.common.js
simplepro/static/admin/simplepro/echarts/echarts-en.common.min.js
simplepro/static/admin/simplepro/echarts/echarts-en.js
simplepro/static/admin/simplepro/echarts/echarts-en.js.map
simplepro/static/admin/simplepro/echarts/echarts-en.min.js
simplepro/static/admin/simplepro/echarts/echarts-en.simple.js
simplepro/static/admin/simplepro/echarts/echarts-en.simple.min.js
simplepro/static/admin/simplepro/echarts/echarts.common.js
simplepro/static/admin/simplepro/echarts/echarts.common.min.js
simplepro/static/admin/simplepro/echarts/echarts.js
