Metadata-Version: 1.1
Name: bawa
Version: 1.4
Summary: 占坑专用
Home-page: https://github.com/newpanjing/simpleui
Author: panjing
Author-email: newpanjing@icloud.com
License: Apache License 2.0
Platform: UNKNOWN
Classifier: Programming Language :: Python :: 3
Classifier: Operating System :: OS Independent
